{
  "version": "4.67.0",
  "application": {
    "aimms.widget.type": {
      "literal": "application"
    },
    "browsername": {
      "aimms": {
        "contents": [
          "webui::ClientBrowserName"
        ]
      }
    },
    "browsertimezone": {
      "aimms": {
        "contents": [
          "webui::BrowserTimeZone"
        ]
      }
    },
    "ignoredst": {
      "aimms": {
        "contents": [
          "webui::IgnoreDST"
        ]
      }
    },
    "pages": {
      "literal": {
        "name": "root",
        "slug": "root",
        "children": [
          {
            "name": "Main Project",
            "slug": "main_project",
            "children": [
              {
                "name": "home",
                "slug": "home",
                "type": "pagev2-grid",
                "children": []
              },
              {
                "name": "Story",
                "type": "pagev2-grid",
                "slug": "story",
                "children": []
              },
              {
                "name": "Network",
                "type": "pagev2-grid",
                "slug": "network",
                "children": [
                  {
                    "name": "Network Help",
                    "type": "pagev2-grid-sidepanel",
                    "slug": "network_help",
                    "children": []
                  }
                ]
              },
              {
                "name": "Tours",
                "type": "pagev2-grid",
                "slug": "tours",
                "children": [
                  {
                    "name": "Heuristic Help",
                    "type": "pagev2-grid-sidepanel",
                    "slug": "heuristic_help",
                    "children": []
                  }
                ]
              },
              {
                "name": "Exact",
                "type": "pagev2-grid",
                "slug": "exact",
                "children": [
                  {
                    "name": "Exact Help",
                    "type": "pagev2-grid-sidepanel",
                    "slug": "exact_help",
                    "children": []
                  }
                ]
              },
              {
                "name": "Comparison",
                "type": "pagev2-grid",
                "slug": "comparison",
                "children": []
              }
            ]
          }
        ]
      }
    },
    "theme.classic": {
      "literal": "NOT_ALLOWED"
    },
    "timezone": {
      "aimms": {
        "contents": [
          "webui::DisplayTimeZone"
        ]
      }
    },
    "timezone.dst.readonly": {
      "aimms": {
        "contents": [
          "webui::DefaultDSTSettingForDisplayTimeZone"
        ]
      }
    },
    "workflows.configuration": {
      "aimms": {
        "contents": [
          "sp_myWorkflowSteps"
        ],
        "slices": [
          {
            "identifier": "sp_myWorkflowSteps",
            "slice": [
              {
                "index": "webui::indexWorkflowOrder",
                "type": "free",
                "value": "webui::indexWorkflowOrder"
              },
              {
                "index": "webui::indexNoOfPages",
                "type": "free",
                "value": "webui::indexNoOfPages"
              },
              {
                "index": "webui::indexWorkflowPageSpec",
                "type": "free",
                "value": "webui::indexWorkflowPageSpec"
              }
            ]
          }
        ]
      }
    },
    "workflows.information": {
      "aimms": {
        "contents": [
          "sp_myWorkflows"
        ],
        "slices": [
          {
            "identifier": "sp_myWorkflows",
            "slice": [
              {
                "index": "webui::indexWorkflowOrder",
                "type": "free",
                "value": "webui::indexWorkflowOrder"
              },
              {
                "index": "webui::indexWorkflowSpec",
                "type": "free",
                "value": "webui::indexWorkflowSpec"
              }
            ]
          }
        ]
      }
    }
  },
  "layouts/custom_a248d3ab-a3fe-4824-b012-651c2a8ec116": {
    "definition": {
      "literal": {
        "componentName": "Grid",
        "props": {
          "gridTemplateColumns": "3fr 0.8fr 0.12fr",
          "gridTemplateRows": "1fr 0.2fr 1fr 0.2fr 1fr 0.2fr",
          "gridTemplateAreas": "\"area-a area-b area-b\" \"area-a area-x area-e\" \"area-a area-c area-c\" \"area-a area-y area-f\" \"area-a area-d area-d\"  \"area-a area-z area-g\""
        },
        "items": [
          {
            "componentName": "WidgetArea",
            "props": {
              "gridArea": "area-a",
              "name": "Area A",
              "gridAutoFlow": "column"
            }
          },
          {
            "componentName": "WidgetArea",
            "props": {
              "gridArea": "area-b",
              "name": "Area B",
              "gridAutoFlow": "row"
            }
          },
          {
            "componentName": "WidgetArea",
            "props": {
              "gridArea": "area-c",
              "name": "Area C",
              "gridAutoFlow": "row"
            }
          },
          {
            "componentName": "WidgetArea",
            "props": {
              "gridArea": "area-d",
              "name": "Area D",
              "gridAutoFlow": "row"
            }
          },
          {
            "componentName": "WidgetArea",
            "props": {
              "gridArea": "area-e",
              "name": "Area E",
              "gridAutoFlow": "row"
            }
          },
          {
            "componentName": "WidgetArea",
            "props": {
              "gridArea": "area-f",
              "name": "Area F",
              "gridAutoFlow": "row"
            }
          },
          {
            "componentName": "WidgetArea",
            "props": {
              "gridArea": "area-g",
              "name": "Area G",
              "gridAutoFlow": "row"
            }
          },
          {
            "componentName": "WidgetArea",
            "props": {
              "gridArea": "area-x",
              "name": "Area X",
              "gridAutoFlow": "row"
            }
          },
          {
            "componentName": "WidgetArea",
            "props": {
              "gridArea": "area-y",
              "name": "Area Y",
              "gridAutoFlow": "row"
            }
          },
          {
            "componentName": "WidgetArea",
            "props": {
              "gridArea": "area-z",
              "name": "Area Z",
              "gridAutoFlow": "row"
            }
          }
        ]
      }
    },
    "displayName": {
      "literal": "NetworkPage"
    }
  },
  "layouts/custom_afa86eba-6e6a-4077-a063-bf443788a472": {
    "definition": {
      "literal": {
        "componentName": "Grid",
        "props": {
          "gridTemplateColumns": "1fr 1fr 1fr",
          "gridTemplateRows": "1fr",
          "gridTemplateAreas": "\"area-a area-b area-c\""
        },
        "items": [
          {
            "componentName": "WidgetArea",
            "props": {
              "gridArea": "area-a",
              "name": "Area A",
              "gridAutoFlow": "row"
            }
          },
          {
            "componentName": "WidgetArea",
            "props": {
              "gridArea": "area-b",
              "name": "Area B",
              "gridAutoFlow": "row"
            }
          },
          {
            "componentName": "WidgetArea",
            "props": {
              "gridArea": "area-c",
              "name": "Area C",
              "gridAutoFlow": "row"
            }
          }
        ]
      }
    },
    "displayName": {
      "literal": "HeuristicPage"
    }
  },
  "layouts/custom_b7eede6d-0fce-408a-b5f0-e9285d41c6a2": {
    "definition": {
      "literal": {
        "componentName": "Grid",
        "props": {
          "gridTemplateColumns": "0.5fr 1fr",
          "gridTemplateRows": "1fr",
          "gridTemplateAreas": "\"area-a area-b\" \"area-a area-b\""
        },
        "items": [
          {
            "componentName": "WidgetArea",
            "props": {
              "gridArea": "area-a",
              "name": "Area A",
              "gridAutoFlow": "row"
            }
          },
          {
            "componentName": "WidgetArea",
            "props": {
              "gridArea": "area-b",
              "name": "Area B",
              "gridAutoFlow": "row"
            }
          }
        ]
      }
    },
    "displayName": {
      "literal": "ComparisonPage"
    }
  },
  "layouts/custom_c76b6978-4f0e-427a-b071-7f46c9cd29f4": {
    "definition": {
      "literal": {
        "componentName": "Grid",
        "props": {
          "gridTemplateColumns": "1fr 1fr",
          "gridTemplateRows": "1fr",
          "gridTemplateAreas": "\"area-a area-b\" \"area-a area-b\""
        },
        "items": [
          {
            "componentName": "WidgetArea",
            "props": {
              "gridArea": "area-a",
              "name": "Area A",
              "gridAutoFlow": "column"
            }
          },
          {
            "componentName": "WidgetArea",
            "props": {
              "gridArea": "area-b",
              "name": "Area B",
              "gridAutoFlow": "column"
            }
          }
        ]
      }
    },
    "displayName": {
      "literal": "ExactPage"
    }
  },
  "pages/comparison": {
    "aimms.widget.type": {
      "literal": "pagev2-grid"
    },
    "bindings": {
      "literal": [
        {
          "widgetUri": "scl_initialTour",
          "gridArea": "area-a",
          "dndId": "area-ascl_initialTour0"
        },
        {
          "widgetUri": "scl_timeComparison",
          "gridArea": "area-a",
          "dndId": "area-ascl_timeComparison1"
        },
        {
          "widgetUri": "cmb_comparison_1",
          "gridArea": "area-b",
          "dndId": "Unassigned widgetscmb_comparison_13"
        },
        {
          "widgetUri": "cmb_comparison",
          "gridArea": "area-b",
          "dndId": "area-bcmb_comparison2"
        }
      ]
    },
    "layoutId": {
      "literal": "custom_b7eede6d-0fce-408a-b5f0-e9285d41c6a2"
    },
    "widgets": {
      "literal": [
        {
          "uri": "scl_initialTour",
          "layoutInfo": {
            "width": "2",
            "height": "1"
          }
        },
        {
          "uri": "scl_timeComparison",
          "layoutInfo": {
            "width": "2",
            "height": "1"
          }
        },
        {
          "uri": "cmb_comparison",
          "layoutInfo": {
            "width": "2",
            "height": "1"
          }
        },
        {
          "uri": "cmb_comparison_1",
          "layoutInfo": {
            "width": "2",
            "height": "1"
          }
        }
      ]
    }
  },
  "pages/exact": {
    "aimms.widget.type": {
      "literal": "pagev2-grid"
    },
    "bindings": {
      "literal": [
        {
          "widgetUri": "map_improvedTourSimultaneous_2",
          "gridArea": "area-b",
          "dndId": "area-amap_improvedTourSimultaneous_21"
        },
        {
          "widgetUri": "map_improvedTourSimultaneous_1",
          "gridArea": "area-a",
          "dndId": "area-amap_improvedTourSimultaneous_10"
        }
      ]
    },
    "layoutId": {
      "literal": "custom_c76b6978-4f0e-427a-b071-7f46c9cd29f4"
    },
    "primarypageaction": {
      "aimms": {
        "contents": [
          "sp_def_exactPrimaryActions"
        ],
        "slices": [
          {
            "identifier": "sp_def_exactPrimaryActions",
            "slice": [
              {
                "index": "webui::indexPageActionSpec",
                "type": "free",
                "value": "webui::indexPageActionSpec"
              }
            ]
          }
        ]
      }
    },
    "sidepanels": {
      "aimms": {
        "contents": [
          "sp_def_exactSidePanel"
        ],
        "slices": [
          {
            "identifier": "sp_def_exactSidePanel",
            "slice": [
              {
                "index": "webui::indexPageExtension",
                "type": "free",
                "value": "webui::indexPageExtension"
              },
              {
                "index": "webui::indexSidePanelSpec",
                "type": "free",
                "value": "webui::indexSidePanelSpec"
              }
            ]
          }
        ]
      }
    },
    "widgets": {
      "literal": [
        {
          "uri": "map_improvedTourSimultaneous_1",
          "layoutInfo": {
            "width": "2",
            "height": "1"
          }
        },
        {
          "uri": "map_improvedTourSimultaneous_2",
          "layoutInfo": {
            "width": "2",
            "height": "1"
          }
        }
      ]
    }
  },
  "pages/home": {
    "aimms.widget.type": {
      "literal": "pagev2-grid"
    },
    "bindings": {
      "literal": [
        {
          "widgetUri": "img_homeLogo",
          "gridArea": "area-d",
          "dndId": "area-aimg_homeLogo1"
        },
        {
          "widgetUri": "txt_welcome",
          "gridArea": "area-a",
          "dndId": "area-atxt_welcome0"
        }
      ]
    },
    "layoutId": {
      "literal": "Layout10"
    },
    "widgets": {
      "literal": [
        {
          "uri": "txt_welcome",
          "layoutInfo": {
            "width": "2",
            "height": "1"
          }
        },
        {
          "uri": "img_homeLogo",
          "layoutInfo": {
            "width": "2",
            "height": "1"
          }
        }
      ]
    }
  },
  "pages/network": {
    "aimms.widget.type": {
      "literal": "pagev2-grid"
    },
    "bindings": {
      "literal": [
        {
          "widgetUri": "btn_addThisCity",
          "gridArea": "area-e",
          "dndId": "area-bbtn_addThisCity5"
        },
        {
          "widgetUri": "btn_addByCountry",
          "gridArea": "area-f",
          "dndId": "area-fbtn_addByCountry0"
        },
        {
          "widgetUri": "btn_addByLimity",
          "gridArea": "area-g",
          "dndId": "area-gbtn_addByLimity1"
        },
        {
          "widgetUri": "scl_newNetworkInfo",
          "gridArea": "Unassigned widgets",
          "dndId": "Unassigned widgetsscl_newNetworkInfo2"
        },
        {
          "widgetUri": "btn_cleanAllNodes",
          "gridArea": "area-b",
          "dndId": "area-bbtn_cleanAllNodes3"
        },
        {
          "widgetUri": "scl_addByCity",
          "gridArea": "area-b",
          "dndId": "area-bscl_addByCity4"
        },
        {
          "widgetUri": "scl_addByCountry",
          "gridArea": "area-c",
          "dndId": "area-cscl_addByCountry6"
        },
        {
          "widgetUri": "scl_addByLimit",
          "gridArea": "area-d",
          "dndId": "area-dscl_addByLimit7"
        },
        {
          "widgetUri": "map_allNodes",
          "gridArea": "area-a",
          "dndId": "area-amap_allNodes8"
        }
      ]
    },
    "layoutId": {
      "literal": "custom_a248d3ab-a3fe-4824-b012-651c2a8ec116"
    },
    "sidepanels": {
      "aimms": {
        "contents": [
          "sp_def_networkSidePanel"
        ],
        "slices": [
          {
            "identifier": "sp_def_networkSidePanel",
            "slice": [
              {
                "index": "webui::indexPageExtension",
                "type": "free",
                "value": "webui::indexPageExtension"
              },
              {
                "index": "webui::indexSidePanelSpec",
                "type": "free",
                "value": "webui::indexSidePanelSpec"
              }
            ]
          }
        ]
      }
    },
    "widgets": {
      "literal": [
        {
          "uri": "scl_newNetworkInfo",
          "layoutInfo": {
            "width": "2",
            "height": "1"
          }
        },
        {
          "uri": "btn_addByLimity",
          "layoutInfo": {
            "width": "2",
            "height": "1"
          }
        },
        {
          "uri": "btn_addByCountry",
          "layoutInfo": {
            "width": "2",
            "height": "1"
          }
        },
        {
          "uri": "btn_addThisCity",
          "layoutInfo": {
            "width": "2",
            "height": "1"
          }
        },
        {
          "uri": "scl_addByLimit",
          "layoutInfo": {
            "width": "2",
            "height": "1"
          }
        },
        {
          "uri": "scl_addByCountry",
          "layoutInfo": {
            "width": "2",
            "height": "1"
          }
        },
        {
          "uri": "scl_addByCity",
          "layoutInfo": {
            "width": "2",
            "height": "1"
          }
        },
        {
          "uri": "btn_cleanAllNodes",
          "layoutInfo": {
            "width": "2",
            "height": "1"
          }
        },
        {
          "uri": "map_allNodes",
          "layoutInfo": {
            "width": "2",
            "height": "1"
          }
        }
      ]
    }
  },
  "pages/network_help": {
    "widgets": {
      "literal": []
    },
    "aimms.widget.type": {
      "literal": "pagev2-grid-sidepanel"
    }
  },
  "pages/story": {
    "aimms.widget.type": {
      "literal": "pagev2-grid"
    },
    "bindings": {
      "literal": [
        {
          "widgetUri": "txt_story",
          "gridArea": "area-a",
          "dndId": "Unassigned widgetstxt_story"
        }
      ]
    },
    "layoutId": {
      "literal": "Layout11"
    },
    "widgets": {
      "literal": [
        {
          "uri": "txt_story",
          "layoutInfo": {
            "width": "2",
            "height": "1"
          }
        }
      ]
    }
  },
  "pages/tours": {
    "aimms.widget.type": {
      "literal": "pagev2-grid"
    },
    "bindings": {
      "literal": [
        {
          "widgetUri": "map_improvedTourCyclic",
          "gridArea": "area-c",
          "dndId": "area-cmap_improvedTourCyclic2"
        },
        {
          "widgetUri": "map_initialTour",
          "gridArea": "area-a",
          "dndId": "area-amap_initialTour4"
        },
        {
          "widgetUri": "map_improvedTourSimultaneous",
          "gridArea": "area-b",
          "dndId": "area-bmap_improvedTourSimultaneous6"
        }
      ]
    },
    "layoutId": {
      "literal": "custom_afa86eba-6e6a-4077-a063-bf443788a472"
    },
    "primarypageaction": {
      "aimms": {
        "contents": [
          "sp_def_heuristicPrimaryActions"
        ],
        "slices": [
          {
            "identifier": "sp_def_heuristicPrimaryActions",
            "slice": [
              {
                "index": "webui::indexPageActionSpec",
                "type": "free",
                "value": "webui::indexPageActionSpec"
              }
            ]
          }
        ]
      }
    },
    "secondarypageactions": {
      "aimms": {
        "contents": [
          "sp_def_heuristicSecondaryActions"
        ],
        "slices": [
          {
            "identifier": "sp_def_heuristicSecondaryActions",
            "slice": [
              {
                "index": "webui::indexPageExtension",
                "type": "free",
                "value": "webui::indexPageExtension"
              },
              {
                "index": "webui::indexPageActionSpec",
                "type": "free",
                "value": "webui::indexPageActionSpec"
              }
            ]
          }
        ]
      }
    },
    "sidepanels": {
      "aimms": {
        "contents": [
          "sp_def_heuristicSidePanel"
        ],
        "slices": [
          {
            "identifier": "sp_def_heuristicSidePanel",
            "slice": [
              {
                "index": "webui::indexPageExtension",
                "type": "free",
                "value": "webui::indexPageExtension"
              },
              {
                "index": "webui::indexSidePanelSpec",
                "type": "free",
                "value": "webui::indexSidePanelSpec"
              }
            ]
          }
        ]
      }
    },
    "widgets": {
      "literal": [
        {
          "uri": "map_initialTour",
          "layoutInfo": {
            "width": "2",
            "height": "1"
          }
        },
        {
          "uri": "map_improvedTourCyclic",
          "layoutInfo": {
            "width": "2",
            "height": "1"
          }
        },
        {
          "uri": "map_improvedTourSimultaneous",
          "layoutInfo": {
            "width": "2",
            "height": "1"
          }
        }
      ]
    }
  },
  "widgets/btn_addByCountry": {
    "action": {
      "literal": {
        "type": "procedure",
        "value": "pr_addByCountry"
      }
    },
    "aimms.widget.type": {
      "literal": "button"
    },
    "name": {
      "literal": "btn_addByCountry"
    },
    "title": {
      "literal": "⚙"
    }
  },
  "widgets/btn_addByLimity": {
    "action": {
      "literal": {
        "type": "procedure",
        "value": "pr_addByLimit"
      }
    },
    "aimms.widget.type": {
      "literal": "button"
    },
    "name": {
      "literal": "btn_addByLimity"
    },
    "title": {
      "literal": "⚙"
    }
  },
  "widgets/btn_addThisCity": {
    "action": {
      "literal": {
        "type": "procedure",
        "value": "pr_addThisCity"
      }
    },
    "aimms.widget.type": {
      "literal": "button"
    },
    "name": {
      "literal": "btn_addThisCity"
    },
    "title": {
      "literal": "⚙"
    }
  },
  "widgets/btn_cleanAllNodes": {
    "action": {
      "literal": {
        "type": "procedure",
        "value": "pr_cleanAllNodes"
      }
    },
    "aimms.widget.type": {
      "literal": "button"
    },
    "name": {
      "literal": "btn_cleanAllNodes"
    },
    "title": {
      "literal": "delete all nodes"
    }
  },
  "widgets/cmb_comparison": {
    "aimms.widget.type": {
      "literal": "combinationchart"
    },
    "contents.__display_order__": {
      "literal": [
        "contents.2",
        "contents.1",
        "contents.4",
        "contents.0",
        "contents.3"
      ]
    },
    "contents.0.identifier": {
      "literal": {
        "identifier": "p_exactTimeElapsed"
      }
    },
    "contents.1.identifier": {
      "literal": {
        "identifier": "p_cyc_timeElapsed"
      }
    },
    "contents.2.identifier": {
      "literal": {
        "identifier": "p_init_timeElapsed"
      }
    },
    "contents.3.identifier": {
      "literal": {
        "identifier": "p_relaxedTimeElapsed"
      }
    },
    "contents.3.show.units": {
      "literal": false
    },
    "contents.4.identifier": {
      "literal": {
        "identifier": "p_sim_timeElapsed"
      }
    },
    "contents.partition": {
      "literal": {
        "header": [
          "<IDENTIFIER-SET>"
        ],
        "grouped": [],
        "stacked": [],
        "aggregated": []
      }
    },
    "contents.show.units": {
      "literal": true
    },
    "data.labels.show": {
      "literal": true
    },
    "indices.__display_order__": {
      "literal": [
        "indices.0"
      ]
    },
    "legend.show": {
      "literal": false
    },
    "name": {
      "literal": "cmb_timeComparison"
    }
  },
  "widgets/cmb_comparison_1": {
    "aimms.widget.type": {
      "literal": "combinationchart"
    },
    "contents.__display_order__": {
      "literal": [
        "contents.2",
        "contents.1",
        "contents.4",
        "contents.0",
        "contents.3"
      ]
    },
    "contents.0.identifier": {
      "literal": {
        "identifier": "p_exactObjective"
      }
    },
    "contents.1.identifier": {
      "literal": {
        "identifier": "p_cyc_tourDistance"
      }
    },
    "contents.2.identifier": {
      "literal": {
        "identifier": "p_init_tourDistance"
      }
    },
    "contents.3.identifier": {
      "literal": {
        "identifier": "p_lowerBound"
      }
    },
    "contents.3.show.units": {
      "literal": false
    },
    "contents.4.identifier": {
      "literal": {
        "identifier": "p_sim_tourDistance"
      }
    },
    "contents.partition": {
      "literal": {
        "header": [
          "<IDENTIFIER-SET>"
        ],
        "grouped": [],
        "stacked": [],
        "aggregated": []
      }
    },
    "contents.show.units": {
      "literal": true
    },
    "data.labels.show": {
      "literal": true
    },
    "indices.__display_order__": {
      "literal": [
        "indices.0"
      ]
    },
    "legend.show": {
      "literal": false
    },
    "name": {
      "literal": "cmb_tourComparison"
    },
    "transparency.index": {
      "literal": "<IDENTIFIER-SET>"
    }
  },
  "widgets/img_homeLogo": {
    "aimms.widget.type": {
      "literal": "image"
    },
    "contents": {
      "aimms": {
        "contents": [
          "sp_logo"
        ]
      }
    },
    "name": {
      "literal": "img_homeLogo"
    }
  },
  "widgets/map_allNodes": {
    "aimms.widget.type": {
      "literal": "map-v2"
    },
    "arcs.__display_order__": {
      "literal": [
        "arcs.0"
      ]
    },
    "center.latitude": {
      "literal": -4.565473550710278
    },
    "center.longitude": {
      "literal": -3.873929061151685
    },
    "contextmenu": {
      "aimms": {
        "contents": [
          "sp_def_nodeItemActions"
        ],
        "slices": [
          {
            "identifier": "sp_def_nodeItemActions",
            "slice": [
              {
                "index": "webui::indexWidgetItemActionSpec",
                "type": "free",
                "value": "webui::indexWidgetItemActionSpec"
              },
              {
                "index": "webui::indexPageExtension",
                "type": "free",
                "value": "webui::indexPageExtension"
              },
              {
                "index": "webui::indexWidgetActionSpec",
                "type": "free",
                "value": "webui::indexWidgetActionSpec"
              }
            ]
          }
        ]
      }
    },
    "name": {
      "literal": "map_allNodes"
    },
    "nodes.__display_order__": {
      "literal": [
        "nodes.0"
      ]
    },
    "nodes.0": {
      "aimms": {
        "contents": [
          "p_longitude",
          "p_latitude",
          "p_def_nodeSize"
        ],
        "slices": [
          {
            "identifier": "p_longitude",
            "slice": [
              {
                "index": "i_city",
                "type": "subset",
                "value": "i_node1"
              }
            ]
          },
          {
            "identifier": "p_latitude",
            "slice": [
              {
                "index": "i_city",
                "type": "subset",
                "value": "i_node1"
              }
            ]
          },
          {
            "identifier": "p_def_nodeSize",
            "slice": [
              {
                "index": "i_city",
                "type": "subset",
                "value": "i_node1"
              }
            ]
          }
        ]
      }
    },
    "nodes.0.index": {
      "literal": {
        "focus": [
          {
            "index": "i_node1",
            "value": "ep_city"
          }
        ],
        "identifier": "i_node1"
      }
    },
    "nodes.0.latitude": {
      "literal": {
        "identifier": "p_latitude",
        "slice": [
          {
            "index": "i_city",
            "type": "subset",
            "value": "i_node1"
          }
        ]
      }
    },
    "nodes.0.longitude": {
      "literal": {
        "identifier": "p_longitude",
        "slice": [
          {
            "index": "i_city",
            "type": "subset",
            "value": "i_node1"
          }
        ]
      }
    },
    "nodes.0.maximumreferencesize": {
      "literal": 30
    },
    "nodes.0.size": {
      "literal": {
        "identifier": "p_def_nodeSize",
        "slice": [
          {
            "index": "i_city",
            "type": "subset",
            "value": "i_node1"
          }
        ]
      }
    },
    "title": {
      "aimms": {
        "contents": [
          "sp_mapTitle"
        ],
        "slices": []
      }
    },
    "zoom": {
      "literal": 2
    }
  },
  "widgets/map_improvedTourCyclic": {
    "aimms.widget.type": {
      "literal": "map-v2"
    },
    "arcs.__display_order__": {
      "literal": [
        "arcs.0"
      ]
    },
    "arcs.0": {
      "aimms": {
        "contents": [
          "p_cyc_tourConnect"
        ],
        "slices": [
          {
            "identifier": "p_cyc_tourConnect",
            "slice": [
              {
                "index": "i_city1",
                "type": "free",
                "value": "i_city1"
              },
              {
                "index": "i_city2",
                "type": "free",
                "value": "i_city2"
              }
            ]
          }
        ]
      }
    },
    "arcs.0.label.hide": {
      "literal": true
    },
    "arcs.0.line.straight": {
      "literal": true
    },
    "arcs.0.value": {
      "literal": {
        "identifier": "p_cyc_tourConnect",
        "slice": [
          {
            "index": "i_city1",
            "type": "free",
            "value": "i_city1"
          },
          {
            "index": "i_city2",
            "type": "free",
            "value": "i_city2"
          }
        ]
      }
    },
    "center.latitude": {
      "literal": -15.453680224345837
    },
    "center.longitude": {
      "literal": -56.14870948379353
    },
    "contextmenu": {
      "aimms": {
        "contents": [
          "sp_def_nodeItemActions"
        ],
        "slices": [
          {
            "identifier": "sp_def_nodeItemActions",
            "slice": [
              {
                "index": "webui::indexWidgetItemActionSpec",
                "type": "free",
                "value": "webui::indexWidgetItemActionSpec"
              },
              {
                "index": "webui::indexPageExtension",
                "type": "free",
                "value": "webui::indexPageExtension"
              },
              {
                "index": "webui::indexWidgetActionSpec",
                "type": "free",
                "value": "webui::indexWidgetActionSpec"
              }
            ]
          }
        ]
      }
    },
    "heatmaps.__display_order__": {
      "literal": [
        "heatmaps.0"
      ]
    },
    "name": {
      "literal": "map_improvedTourCyclic"
    },
    "nodes.__display_order__": {
      "literal": [
        "nodes.0"
      ]
    },
    "nodes.0": {
      "aimms": {
        "contents": [
          "p_longitude",
          "p_latitude",
          "p_def_nodeSize"
        ],
        "slices": [
          {
            "identifier": "p_longitude",
            "slice": [
              {
                "index": "i_city",
                "type": "subset",
                "value": "i_node1"
              }
            ]
          },
          {
            "identifier": "p_latitude",
            "slice": [
              {
                "index": "i_city",
                "type": "subset",
                "value": "i_node1"
              }
            ]
          },
          {
            "identifier": "p_def_nodeSize",
            "slice": [
              {
                "index": "i_city",
                "type": "subset",
                "value": "i_node1"
              }
            ]
          }
        ]
      }
    },
    "nodes.0.index": {
      "literal": {
        "identifier": "i_node1",
        "focus": [
          {
            "index": "i_node1",
            "value": "ep_city"
          }
        ]
      }
    },
    "nodes.0.latitude": {
      "literal": {
        "identifier": "p_latitude",
        "slice": [
          {
            "index": "i_city",
            "type": "subset",
            "value": "i_node1"
          }
        ]
      }
    },
    "nodes.0.longitude": {
      "literal": {
        "identifier": "p_longitude",
        "slice": [
          {
            "index": "i_city",
            "type": "subset",
            "value": "i_node1"
          }
        ]
      }
    },
    "nodes.0.maximumreferencesize": {
      "literal": 30
    },
    "nodes.0.size": {
      "literal": {
        "identifier": "p_def_nodeSize",
        "slice": [
          {
            "index": "i_city",
            "type": "subset",
            "value": "i_node1"
          }
        ]
      }
    },
    "title": {
      "aimms": {
        "contents": [
          "sp_titleImprovedTourCyclic"
        ],
        "slices": []
      }
    },
    "zoom": {
      "literal": 2
    }
  },
  "widgets/map_improvedTourSimultaneous": {
    "aimms.widget.type": {
      "literal": "map-v2"
    },
    "arcs.__display_order__": {
      "literal": [
        "arcs.0"
      ]
    },
    "arcs.0": {
      "aimms": {
        "contents": [
          "p_sim_tourConnect"
        ],
        "slices": [
          {
            "identifier": "p_sim_tourConnect",
            "slice": [
              {
                "index": "i_city1",
                "type": "free",
                "value": "i_city1"
              },
              {
                "index": "i_city2",
                "type": "free",
                "value": "i_city2"
              }
            ]
          }
        ]
      }
    },
    "arcs.0.label.hide": {
      "literal": true
    },
    "arcs.0.line.straight": {
      "literal": true
    },
    "arcs.0.value": {
      "literal": {
        "identifier": "p_sim_tourConnect",
        "slice": [
          {
            "index": "i_city1",
            "type": "free",
            "value": "i_city1"
          },
          {
            "index": "i_city2",
            "type": "free",
            "value": "i_city2"
          }
        ]
      }
    },
    "center.latitude": {
      "literal": -0.8788717828324149
    },
    "center.longitude": {
      "literal": -62.952248891541618
    },
    "contextmenu": {
      "aimms": {
        "contents": [
          "sp_def_nodeItemActions"
        ],
        "slices": [
          {
            "identifier": "sp_def_nodeItemActions",
            "slice": [
              {
                "index": "webui::indexWidgetItemActionSpec",
                "type": "free",
                "value": "webui::indexWidgetItemActionSpec"
              },
              {
                "index": "webui::indexPageExtension",
                "type": "free",
                "value": "webui::indexPageExtension"
              },
              {
                "index": "webui::indexWidgetActionSpec",
                "type": "free",
                "value": "webui::indexWidgetActionSpec"
              }
            ]
          }
        ]
      }
    },
    "heatmaps.__display_order__": {
      "literal": [
        "heatmaps.0"
      ]
    },
    "name": {
      "literal": "map_improvedTourSimultaneous"
    },
    "nodes.__display_order__": {
      "literal": [
        "nodes.0"
      ]
    },
    "nodes.0": {
      "aimms": {
        "contents": [
          "p_longitude",
          "p_latitude",
          "p_def_nodeSize"
        ],
        "slices": [
          {
            "identifier": "p_longitude",
            "slice": [
              {
                "index": "i_city",
                "type": "subset",
                "value": "i_node1"
              }
            ]
          },
          {
            "identifier": "p_latitude",
            "slice": [
              {
                "index": "i_city",
                "type": "subset",
                "value": "i_node1"
              }
            ]
          },
          {
            "identifier": "p_def_nodeSize",
            "slice": [
              {
                "index": "i_city",
                "type": "subset",
                "value": "i_node1"
              }
            ]
          }
        ]
      }
    },
    "nodes.0.index": {
      "literal": {
        "identifier": "i_node1",
        "focus": [
          {
            "index": "i_node1",
            "value": "ep_city"
          }
        ]
      }
    },
    "nodes.0.latitude": {
      "literal": {
        "identifier": "p_latitude",
        "slice": [
          {
            "index": "i_city",
            "type": "subset",
            "value": "i_node1"
          }
        ]
      }
    },
    "nodes.0.longitude": {
      "literal": {
        "identifier": "p_longitude",
        "slice": [
          {
            "index": "i_city",
            "type": "subset",
            "value": "i_node1"
          }
        ]
      }
    },
    "nodes.0.maximumreferencesize": {
      "literal": 30
    },
    "nodes.0.size": {
      "literal": {
        "identifier": "p_def_nodeSize",
        "slice": [
          {
            "index": "i_city",
            "type": "subset",
            "value": "i_node1"
          }
        ]
      }
    },
    "title": {
      "literal": "Improved Tour (Simultaneous)"
    },
    "zoom": {
      "literal": 2
    }
  },
  "widgets/map_improvedTourSimultaneous_1": {
    "aimms.widget.type": {
      "literal": "map-v2"
    },
    "arcs.__display_order__": {
      "literal": [
        "arcs.0"
      ]
    },
    "arcs.0": {
      "aimms": {
        "contents": [
          "p_calc_solutionTour"
        ],
        "slices": [
          {
            "identifier": "p_calc_solutionTour",
            "slice": [
              {
                "index": "i_node1",
                "type": "free",
                "value": "i_node1"
              },
              {
                "index": "i_node2",
                "type": "free",
                "value": "i_node2"
              }
            ]
          }
        ]
      }
    },
    "arcs.0.label.hide": {
      "literal": true
    },
    "arcs.0.line.straight": {
      "literal": true
    },
    "arcs.0.value": {
      "literal": {
        "identifier": "p_calc_solutionTour",
        "slice": [
          {
            "index": "i_node1",
            "type": "free",
            "value": "i_node1"
          },
          {
            "index": "i_node2",
            "type": "free",
            "value": "i_node2"
          }
        ]
      }
    },
    "center.latitude": {
      "literal": -16.003575733881314
    },
    "center.longitude": {
      "literal": -52.20703125000001
    },
    "contextmenu": {
      "aimms": {
        "contents": [
          "sp_def_nodeItemActions"
        ],
        "slices": [
          {
            "identifier": "sp_def_nodeItemActions",
            "slice": [
              {
                "index": "webui::indexWidgetItemActionSpec",
                "type": "free",
                "value": "webui::indexWidgetItemActionSpec"
              },
              {
                "index": "webui::indexPageExtension",
                "type": "free",
                "value": "webui::indexPageExtension"
              },
              {
                "index": "webui::indexWidgetActionSpec",
                "type": "free",
                "value": "webui::indexWidgetActionSpec"
              }
            ]
          }
        ]
      }
    },
    "heatmaps.__display_order__": {
      "literal": [
        "heatmaps.0"
      ]
    },
    "name": {
      "literal": "map_exactTour"
    },
    "nodes.__display_order__": {
      "literal": [
        "nodes.0"
      ]
    },
    "nodes.0": {
      "aimms": {
        "contents": [
          "p_longitude",
          "p_latitude",
          "p_def_nodeSize"
        ],
        "slices": [
          {
            "identifier": "p_longitude",
            "slice": [
              {
                "index": "i_city",
                "type": "subset",
                "value": "i_node1"
              }
            ]
          },
          {
            "identifier": "p_latitude",
            "slice": [
              {
                "index": "i_city",
                "type": "subset",
                "value": "i_node1"
              }
            ]
          },
          {
            "identifier": "p_def_nodeSize",
            "slice": [
              {
                "index": "i_city",
                "type": "subset",
                "value": "i_node1"
              }
            ]
          }
        ]
      }
    },
    "nodes.0.index": {
      "literal": {
        "identifier": "i_node1",
        "focus": [
          {
            "index": "i_node1",
            "value": "ep_city"
          }
        ]
      }
    },
    "nodes.0.latitude": {
      "literal": {
        "identifier": "p_latitude",
        "slice": [
          {
            "index": "i_city",
            "type": "subset",
            "value": "i_node1"
          }
        ]
      }
    },
    "nodes.0.longitude": {
      "literal": {
        "identifier": "p_longitude",
        "slice": [
          {
            "index": "i_city",
            "type": "subset",
            "value": "i_node1"
          }
        ]
      }
    },
    "nodes.0.maximumreferencesize": {
      "literal": 30
    },
    "nodes.0.size": {
      "literal": {
        "identifier": "p_def_nodeSize",
        "slice": [
          {
            "index": "i_city",
            "type": "subset",
            "value": "i_node1"
          }
        ]
      }
    },
    "title": {
      "literal": "MIP without subtours"
    },
    "zoom": {
      "literal": 4
    }
  },
  "widgets/map_improvedTourSimultaneous_2": {
    "aimms.widget.type": {
      "literal": "map-v2"
    },
    "arcs.__display_order__": {
      "literal": [
        "arcs.0"
      ]
    },
    "arcs.0": {
      "aimms": {
        "contents": [
          "p_relaxedTourSolution"
        ],
        "slices": [
          {
            "identifier": "p_relaxedTourSolution",
            "slice": [
              {
                "index": "i_node1",
                "type": "free",
                "value": "i_node1"
              },
              {
                "index": "i_node2",
                "type": "free",
                "value": "i_node2"
              }
            ]
          }
        ]
      }
    },
    "arcs.0.label.hide": {
      "literal": true
    },
    "arcs.0.line.straight": {
      "literal": true
    },
    "arcs.0.value": {
      "literal": {
        "identifier": "p_relaxedTourSolution",
        "slice": [
          {
            "index": "i_node1",
            "type": "free",
            "value": "i_node1"
          },
          {
            "index": "i_node2",
            "type": "free",
            "value": "i_node2"
          }
        ]
      }
    },
    "center.latitude": {
      "literal": -17.35063837604883
    },
    "center.longitude": {
      "literal": -59.67773437500001
    },
    "contextmenu": {
      "aimms": {
        "contents": [
          "sp_def_nodeItemActions"
        ],
        "slices": [
          {
            "identifier": "sp_def_nodeItemActions",
            "slice": [
              {
                "index": "webui::indexWidgetItemActionSpec",
                "type": "free",
                "value": "webui::indexWidgetItemActionSpec"
              },
              {
                "index": "webui::indexPageExtension",
                "type": "free",
                "value": "webui::indexPageExtension"
              },
              {
                "index": "webui::indexWidgetActionSpec",
                "type": "free",
                "value": "webui::indexWidgetActionSpec"
              }
            ]
          }
        ]
      }
    },
    "heatmaps.__display_order__": {
      "literal": [
        "heatmaps.0"
      ]
    },
    "name": {
      "literal": "map_lowerBoundTour"
    },
    "nodes.__display_order__": {
      "literal": [
        "nodes.0"
      ]
    },
    "nodes.0": {
      "aimms": {
        "contents": [
          "p_longitude",
          "p_latitude",
          "p_def_nodeSize"
        ],
        "slices": [
          {
            "identifier": "p_longitude",
            "slice": [
              {
                "index": "i_city",
                "type": "subset",
                "value": "i_node1"
              }
            ]
          },
          {
            "identifier": "p_latitude",
            "slice": [
              {
                "index": "i_city",
                "type": "subset",
                "value": "i_node1"
              }
            ]
          },
          {
            "identifier": "p_def_nodeSize",
            "slice": [
              {
                "index": "i_city",
                "type": "subset",
                "value": "i_node1"
              }
            ]
          }
        ]
      }
    },
    "nodes.0.index": {
      "literal": {
        "identifier": "i_node1",
        "focus": [
          {
            "index": "i_node1",
            "value": "ep_city"
          }
        ]
      }
    },
    "nodes.0.latitude": {
      "literal": {
        "identifier": "p_latitude",
        "slice": [
          {
            "index": "i_city",
            "type": "subset",
            "value": "i_node1"
          }
        ]
      }
    },
    "nodes.0.longitude": {
      "literal": {
        "identifier": "p_longitude",
        "slice": [
          {
            "index": "i_city",
            "type": "subset",
            "value": "i_node1"
          }
        ]
      }
    },
    "nodes.0.maximumreferencesize": {
      "literal": 30
    },
    "nodes.0.size": {
      "literal": {
        "identifier": "p_def_nodeSize",
        "slice": [
          {
            "index": "i_city",
            "type": "subset",
            "value": "i_node1"
          }
        ]
      }
    },
    "title": {
      "literal": "MIP may contain subtours"
    },
    "zoom": {
      "literal": 4
    }
  },
  "widgets/map_initialTour": {
    "aimms.widget.type": {
      "literal": "map-v2"
    },
    "arcs.__display_order__": {
      "literal": [
        "arcs.0"
      ]
    },
    "arcs.0": {
      "aimms": {
        "contents": [
          "p_init_tourConnect"
        ],
        "slices": [
          {
            "identifier": "p_init_tourConnect",
            "slice": [
              {
                "index": "i_node1",
                "type": "free",
                "value": "i_node1"
              },
              {
                "index": "i_node2",
                "type": "free",
                "value": "i_node2"
              }
            ]
          }
        ]
      }
    },
    "arcs.0.label.hide": {
      "literal": true
    },
    "arcs.0.line.straight": {
      "literal": true
    },
    "arcs.0.value": {
      "literal": {
        "identifier": "p_init_tourConnect",
        "slice": [
          {
            "index": "i_node1",
            "type": "free",
            "value": "i_node1"
          },
          {
            "index": "i_node2",
            "type": "free",
            "value": "i_node2"
          }
        ]
      }
    },
    "arcs.0.width.dynamic": {
      "literal": false
    },
    "center.latitude": {
      "literal": -22.350075806124854
    },
    "center.longitude": {
      "literal": -59.33160012669747
    },
    "contextmenu": {
      "aimms": {
        "contents": [
          "sp_def_nodeItemActions"
        ],
        "slices": [
          {
            "identifier": "sp_def_nodeItemActions",
            "slice": [
              {
                "index": "webui::indexWidgetItemActionSpec",
                "type": "free",
                "value": "webui::indexWidgetItemActionSpec"
              },
              {
                "index": "webui::indexPageExtension",
                "type": "free",
                "value": "webui::indexPageExtension"
              },
              {
                "index": "webui::indexWidgetActionSpec",
                "type": "free",
                "value": "webui::indexWidgetActionSpec"
              }
            ]
          }
        ]
      }
    },
    "heatmaps.__display_order__": {
      "literal": [
        "heatmaps.0"
      ]
    },
    "name": {
      "literal": "map_initialTour"
    },
    "nodes.__display_order__": {
      "literal": [
        "nodes.0"
      ]
    },
    "nodes.0": {
      "aimms": {
        "contents": [
          "p_longitude",
          "p_latitude",
          "p_def_nodeSize"
        ],
        "slices": [
          {
            "identifier": "p_longitude",
            "slice": [
              {
                "index": "i_city",
                "type": "subset",
                "value": "i_node1"
              }
            ]
          },
          {
            "identifier": "p_latitude",
            "slice": [
              {
                "index": "i_city",
                "type": "subset",
                "value": "i_node1"
              }
            ]
          },
          {
            "identifier": "p_def_nodeSize",
            "slice": [
              {
                "index": "i_city",
                "type": "subset",
                "value": "i_node1"
              }
            ]
          }
        ]
      }
    },
    "nodes.0.index": {
      "literal": {
        "identifier": "i_node1",
        "focus": [
          {
            "index": "i_node1",
            "value": "ep_city"
          }
        ]
      }
    },
    "nodes.0.latitude": {
      "literal": {
        "identifier": "p_latitude",
        "slice": [
          {
            "index": "i_city",
            "type": "subset",
            "value": "i_node1"
          }
        ]
      }
    },
    "nodes.0.longitude": {
      "literal": {
        "identifier": "p_longitude",
        "slice": [
          {
            "index": "i_city",
            "type": "subset",
            "value": "i_node1"
          }
        ]
      }
    },
    "nodes.0.maximumreferencesize": {
      "literal": 30
    },
    "nodes.0.size": {
      "literal": {
        "identifier": "p_def_nodeSize",
        "slice": [
          {
            "index": "i_city",
            "type": "subset",
            "value": "i_node1"
          }
        ]
      }
    },
    "title": {
      "literal": "Initial Tour"
    },
    "zoom": {
      "literal": 3
    }
  },
  "widgets/scl_addByCity": {
    "aimms.widget.type": {
      "literal": "scalar"
    },
    "contents": {
      "aimms": {
        "contents": [
          "sp_addThisCity"
        ]
      }
    },
    "name": {
      "literal": "scl_addByCity"
    },
    "title": {
      "literal": "Add by City"
    }
  },
  "widgets/scl_addByCountry": {
    "aimms.widget.type": {
      "literal": "scalar"
    },
    "contents": {
      "aimms": {
        "contents": [
          "p_maxCities",
          "sp_addByCountry"
        ]
      }
    },
    "contents.numdecimals": {
      "literal": 0
    },
    "name": {
      "literal": "scl_addByCountry"
    },
    "title": {
      "literal": "Add by Country"
    }
  },
  "widgets/scl_addByLimit": {
    "aimms.widget.type": {
      "literal": "scalar"
    },
    "contents": {
      "aimms": {
        "contents": [
          "p_maxCities"
        ]
      }
    },
    "contents.numdecimals": {
      "literal": 0
    },
    "name": {
      "literal": "scl_addByLimit"
    },
    "title": {
      "literal": "Add by Limit"
    }
  },
  "widgets/scl_initialTour": {
    "aimms.widget.type": {
      "literal": "scalar"
    },
    "contents": {
      "aimms": {
        "contents": [
          "p_init_tourDistance",
          "p_cyc_tourDistance",
          "p_sim_tourDistance",
          "p_exactObjective",
          "p_lowerBound"
        ]
      }
    },
    "contents.numdecimals": {
      "literal": 3
    },
    "custom.column.widths": {
      "literal": [
        {
          "type": "colHeader",
          "colKey": {},
          "width": 26.23
        },
        {
          "type": "rowHeader",
          "colKey": "<IDENTIFIER-SET>",
          "width": 39.5
        }
      ]
    },
    "multi.line": {
      "literal": 1
    },
    "name": {
      "literal": "scl_tourDistances"
    },
    "title": {
      "literal": "Total Distance per Solve Type"
    }
  },
  "widgets/scl_newNetworkInfo": {
    "aimms.widget.type": {
      "literal": "scalar"
    },
    "contents": {
      "aimms": {
        "contents": [
          "p_def_cardinalityOfNodes",
          "p_def_unableToFetch",
          "p_def_iterationLimit",
          "p_def_maxNeighbors"
        ]
      }
    },
    "contents.numdecimals": {
      "literal": 0
    },
    "name": {
      "literal": "scl_newNetworkInfo"
    }
  },
  "widgets/scl_timeComparison": {
    "aimms.widget.type": {
      "literal": "scalar"
    },
    "contents": {
      "aimms": {
        "contents": [
          "p_init_timeElapsed",
          "p_cyc_timeElapsed",
          "p_sim_timeElapsed",
          "p_exactTimeElapsed",
          "p_relaxedTimeElapsed"
        ]
      }
    },
    "contents.numdecimals": {
      "literal": 4
    },
    "name": {
      "literal": "scl_timeComparison"
    },
    "title": {
      "literal": "Total time per solve type "
    }
  },
  "widgets/txt_story": {
    "aimms.widget.type": {
      "literal": "text"
    },
    "contents": {
      "literal": "<div><span style=\"font-size: 32px;\"><b>Story&nbsp;</b></span></div><div><br></div><div><span style=\"font-size: 18px;\">This example illustrates some of AIMMS control flow statements by means of the traveling salesman 2-opt heuristic. </span></div><div><span style=\"font-size: 18px;\">In the model tree, you will find some declarations to define the problem. In addition, you will find:</span></div><div><br></div><ul><li><span style=\"font-size: 18px;\">A procedure and some declarations to compute and visualize an initial tour constructed by starting at some city and successively selecting the next city as the closest city not yet part of the tour.</span></li><li><span style=\"font-size: 18px;\">A procedure and some declarations to compute and visualize an improved tour constructed by repetitively swapping those two arcs in the tour by means of the 2-opt heuristic that give the largest overall distance improvement, until no further improvement is possible or the iteration limit is reached.</span></li><li><span style=\"font-size: 18px;\">A procedure and some declarations to compute and visualize an improved tour constructed by repetitively swapping the next arc in the (modified) tour with that neighbor arc which gives the largest distance improvement, until the iteration limit is reached or a full cycle over the tour gives no further improvement.</span></li></ul><div><br></div><div><span style=\"font-size: 18px;\">When you run the procedures, the information in the progress window is updated by the functions in the GMP Progress Window library.</span></div>"
    },
    "name": {
      "literal": "txt_story"
    }
  },
  "widgets/txt_welcome": {
    "aimms.widget.type": {
      "literal": "text"
    },
    "contents": {
      "literal": "<div><span style=\"background-color: inherit; font-size: 32px;\"><b>Welcome!</b></span></div><div><br></div><div><span style=\"background-color: inherit; font-size: 18px;\">You are in an AIMMS Example. Feel free to play around and create something more in this app!</span></div><div><span style=\"background-color: inherit; font-size: 18px;\">&nbsp;</span></div><div><span style=\"background-color: inherit; font-size: 18px;\">If you do, please fork this repository and commit your changes.&nbsp;</span><b><span style=\"background-color: inherit; font-size: 18px;\">This ensures our GitHub stays up-to-date for the entire community!</span></b></div><div><br></div><div><span style=\"background-color: inherit; font-size: 18px;\">You can also check our other interactive resources:</span></div><div><br></div><ul><li><span style=\"background-color: inherit; font-size: 18px;\">In the Online&nbsp;</span><a href=\"https://community.aimms.com/\" style=\"color: var(--primaryDarker); background-color: inherit; font-size: 18px;\" target=\"_blank\">Community</a><span style=\"background-color: inherit; font-size: 18px;\">, talk to other developers and AIMMSians about the product, modeling, use cases, and more.</span></li><li><span style=\"background-color: inherit; font-size: 18px;\">In the&nbsp;</span><a href=\"https://academy.aimms.com/\" style=\"color: var(--primaryDarker); background-color: inherit; font-size: 18px;\" target=\"_blank\">Academy</a><span style=\"background-color: inherit; font-size: 18px;\">, learn new skills and challenge yourself. We are busy creating new courses, so keep an eye out!</span></li></ul><div><br></div><div><span style=\"background-color: inherit; font-size: 18px;\">For questions that can't be posted on the community, contact us at&nbsp;</span><i style=\"background-color: rgb(255, 255, 204); font-size: 18px;\">support@aimms.com</i><span style=\"background-color: inherit; font-size: 18px;\">.</span></div><div><br></div><div><br></div><div><br></div><div><br></div><div><br></div><div><br></div><div><br></div>"
    },
    "name": {
      "literal": "txt_welcome"
    }
  }
}